cypherseed/__init__.py
cypherseed/__main__.py
cypherseed/cli.py
cypherseed/generator.py
cypherseed/password_strength.py
cypherseed/utils.py
cypherseed/wordlists.py
cypherseed/wordlists/default.txt
cypherseed/wordlists/diceware_wordlist.txt
cypherseed/wordlists/eff_large_wordlist.txt
cypherseed/wordlists/eff_short_wordlist.txt
cypherseed-0.1.1.dist-info/licenses/LICENSE
cypherseed-0.1.1.dist-info/METADATA
cypherseed-0.1.1.dist-info/WHEEL
cypherseed-0.1.1.dist-info/entry_points.txt
cypherseed-0.1.1.dist-info/top_level.txt
cypherseed-0.1.1.dist-info/RECORD
