Metadata-Version: 2.4
Name: cypherseed
Version: 0.1.1
Summary: Simple high-entropy passphrase generation tool
Author-email: fidacura <hey@fidacura.net>
Maintainer-email: fidacura <hey@fidacura.net>
License:                     GNU GENERAL PUBLIC LICENSE
Project-URL: Homepage, https://github.com/fidacura/cypherseed
Project-URL: Repository, https://github.com/fidacura/cypherseed
Project-URL: Documentation, https://github.com/fidacura/cypherseed#readme
Project-URL: Changelog, https://github.com/fidacura/cypherseed/releases
Project-URL: Bug Tracker, https://github.com/fidacura/cypherseed/issues
Keywords: passphrase,password,security,cryptography,entropy,wordlist,diceware,cli
Classifier: Development Status :: 4 - Beta
Classifier: Environment :: Console
Classifier: Intended Audience :: End Users/Desktop
Classifier: Intended Audience :: System Administrators
Classifier: License :: OSI Approved :: GNU General Public License v2 (GPLv2)
Classifier: Operating System :: OS Independent
Classifier: Programming Language :: Python :: 3
Classifier: Programming Language :: Python :: 3.8
Classifier: Programming Language :: Python :: 3.9
Classifier: Programming Language :: Python :: 3.10
Classifier: Programming Language :: Python :: 3.11
Classifier: Programming Language :: Python :: 3.12
Classifier: Topic :: Security
Classifier: Topic :: Security :: Cryptography
Classifier: Topic :: System :: Systems Administration :: Authentication/Directory
Classifier: Topic :: Utilities
Classifier: Typing :: Typed
Requires-Python: >=3.8
License-File: LICENSE
Requires-Dist: requests>=2.25.0
Provides-Extra: dev
Requires-Dist: pytest>=6.0; extra == "dev"
Requires-Dist: pytest-cov>=2.0; extra == "dev"
Requires-Dist: black>=22.0; extra == "dev"
Requires-Dist: flake8>=4.0; extra == "dev"
Requires-Dist: mypy>=0.900; extra == "dev"
Requires-Dist: isort>=5.0; extra == "dev"
Dynamic: license-file
